stackifier/__init__.py
stackifier/adapters.py
stackifier/models.py
stackifier/stack.py
stackifier/storage.py
stackifier/trace.py
stackifier/utils.py
stackifier/integrations/__init__.py
stackifier/integrations/langchain_integration.py
stackifier/integrations/langgraph_integration.py
stackifier/integrations/litellm_integration.py
stackifier/integrations/openrouter_integration.py
stackifier-1.0.1.dist-info/licenses/LICENSE
stackifier-1.0.1.dist-info/METADATA
stackifier-1.0.1.dist-info/WHEEL
stackifier-1.0.1.dist-info/top_level.txt
stackifier-1.0.1.dist-info/RECORD
