Metadata-Version: 2.4
Name: stackifier
Version: 1.0.1
Summary: Lightweight data collection library for WhatsApp AI agents - log conversations, tool calls, and metrics to JSONL or S3
Author-email: BryanTheLai <owner@bryanslab.com>
License: MIT
Project-URL: Homepage, https://github.com/BryanTheLai/pip-stackifier
Project-URL: Repository, https://github.com/BryanTheLai/pip-stackifier
Requires-Python: >=3.10
License-File: LICENSE
Provides-Extra: dev
Requires-Dist: pytest>=7.0.0; extra == "dev"
Requires-Dist: pytest-cov>=4.0.0; extra == "dev"
Provides-Extra: s3
Requires-Dist: boto3>=1.29.0; extra == "s3"
Provides-Extra: langchain
Requires-Dist: langchain>=0.1.0; extra == "langchain"
Provides-Extra: langgraph
Requires-Dist: langgraph>=0.1.0; extra == "langgraph"
Provides-Extra: litellm
Requires-Dist: litellm>=1.0.0; extra == "litellm"
Provides-Extra: all
Requires-Dist: boto3>=1.29.0; extra == "all"
Requires-Dist: langchain>=0.1.0; extra == "all"
Requires-Dist: langgraph>=0.1.0; extra == "all"
Requires-Dist: litellm>=1.0.0; extra == "all"
Requires-Dist: pytest>=7.0.0; extra == "all"
Requires-Dist: pytest-cov>=4.0.0; extra == "all"
Provides-Extra: test
Requires-Dist: pytest>=7.0.0; extra == "test"
Requires-Dist: pytest-cov>=4.0.0; extra == "test"
Dynamic: license-file
